{"Modules":[{"Key":"","Source":"","Dir":"."},{"Key":"aws_eks_1","Source":"./modules/aws-eks-1","Dir":"modules/aws-eks-1"},{"Key":"aws_eks_2","Source":"./modules/aws-eks-2","Dir":"modules/aws-eks-2"},{"Key":"aws_vpc_1","Source":"./modules/aws-vpc-1","Dir":"modules/aws-vpc-1"},{"Key":"aws_vpc_2","Source":"./modules/aws-vpc-2","Dir":"modules/aws-vpc-2"},{"Key":"azure_aks_1","Source":"./modules/aws-aks-1","Dir":""},{"Key":"azure_vnet_1","Source":"./modules/azure-vnet-1","Dir":"modules/azure-vnet-1"}]}